{
    "GLAMIRA Earring Gaisma - B": {
        "14K Yellow Gold & Emerald": {
            "Product Name": "GLAMIRA Earring Gaisma - B",
            "Product ID": "159474",
            "Product Full Link": "https://www.glamira.com/glamira-earring-gaisma-b.html?alloy=yellow-585&stone1=emerald",
            "Category ID": "1039",
            "Price": "$379.00",
            "Carat": "0.06 crt  - AAA",
            "Detail": {
                "alloy": "yellow-585",
                "stone1": "emerald"
            },
            "Descript": "14K Yellow Gold & Emerald",
            "Product Image Path": [
                "D:\\VScode\\DE\\crawl_data\\Beautifulsoup\\Glamira\\project_glamira\\photo\\image_159474_GLAMIRA-Earring-Gaisma---B_alloy=yellow-585&stone1=emerald_1",
                "D:\\VScode\\DE\\crawl_data\\Beautifulsoup\\Glamira\\project_glamira\\photo\\image_159474_GLAMIRA-Earring-Gaisma---B_alloy=yellow-585&stone1=emerald_2",
                "D:\\VScode\\DE\\crawl_data\\Beautifulsoup\\Glamira\\project_glamira\\photo\\image_159474_GLAMIRA-Earring-Gaisma---B_alloy=yellow-585&stone1=emerald_3",
                "D:\\VScode\\DE\\crawl_data\\Beautifulsoup\\Glamira\\project_glamira\\photo\\image_159474_GLAMIRA-Earring-Gaisma---B_alloy=yellow-585&stone1=emerald_4"
            ]
        }
    },
    "GLAMIRA Earring Varandus": {
        "14K Yellow Gold & Brown Diamond & Diamond": {
            "Product Name": "GLAMIRA Earring Varandus",
            "Product ID": "149768",
            "Product Full Link": "https://www.glamira.com/glamira-earring-varandus.html?accent=olivegreen&alloy=yellow-585&stone1=browndiamond&stone2=diamond-Brillant",
            "Category ID": "1039",
            "Price": "$971.00",
            "Carat": "0.26 crt  - VS1",
            "Detail": {
                "accent": "olivegreen",
                "alloy": "yellow-585",
                "stone1": "browndiamond",
                "stone2": "diamond-Brillant"
            },
            "Descript": "14K Yellow Gold & Brown Diamond & Diamond",
            "Product Image Path": [
                "D:\\VScode\\DE\\crawl_data\\Beautifulsoup\\Glamira\\project_glamira\\photo\\image_149768_GLAMIRA-Earring-Varandus_accent=olivegreen&alloy=yellow-585&stone1=browndiamond&stone2=diamond-Brillant_1",
                "D:\\VScode\\DE\\crawl_data\\Beautifulsoup\\Glamira\\project_glamira\\photo\\image_149768_GLAMIRA-Earring-Varandus_accent=olivegreen&alloy=yellow-585&stone1=browndiamond&stone2=diamond-Brillant_2",
                "D:\\VScode\\DE\\crawl_data\\Beautifulsoup\\Glamira\\project_glamira\\photo\\image_149768_GLAMIRA-Earring-Varandus_accent=olivegreen&alloy=yellow-585&stone1=browndiamond&stone2=diamond-Brillant_3",
                "D:\\VScode\\DE\\crawl_data\\Beautifulsoup\\Glamira\\project_glamira\\photo\\image_149768_GLAMIRA-Earring-Varandus_accent=olivegreen&alloy=yellow-585&stone1=browndiamond&stone2=diamond-Brillant_4"
            ]
        },
        "14K Yellow Gold & Swarovski Green & Swarovski Crystal": {
            "Product Name": "GLAMIRA Earring Varandus",
            "Product ID": "149768",
            "Product Full Link": "https://www.glamira.com/glamira-earring-varandus.html?accent=olivegreen&alloy=yellow-585&stone1=emerald-Swarovsky&stone2=diamond-Swarovsky",
            "Category ID": "1039",
            "Price": "$641.00",
            "Carat": "0.26 crt  - AAAAA",
            "Detail": {
                "accent": "olivegreen",
                "alloy": "yellow-585",
                "stone1": "emerald-Swarovsky",
                "stone2": "diamond-Swarovsky"
            },
            "Descript": "14K Yellow Gold & Swarovski Green & Swarovski Crystal",
            "Product Image Path": [
                "D:\\VScode\\DE\\crawl_data\\Beautifulsoup\\Glamira\\project_glamira\\photo\\image_149768_GLAMIRA-Earring-Varandus_accent=olivegreen&alloy=yellow-585&stone1=emerald-Swarovsky&stone2=diamond-Swarovsky_1",
                "D:\\VScode\\DE\\crawl_data\\Beautifulsoup\\Glamira\\project_glamira\\photo\\image_149768_GLAMIRA-Earring-Varandus_accent=olivegreen&alloy=yellow-585&stone1=emerald-Swarovsky&stone2=diamond-Swarovsky_2",
                "D:\\VScode\\DE\\crawl_data\\Beautifulsoup\\Glamira\\project_glamira\\photo\\image_149768_GLAMIRA-Earring-Varandus_accent=olivegreen&alloy=yellow-585&stone1=emerald-Swarovsky&stone2=diamond-Swarovsky_3",
                "D:\\VScode\\DE\\crawl_data\\Beautifulsoup\\Glamira\\project_glamira\\photo\\image_149768_GLAMIRA-Earring-Varandus_accent=olivegreen&alloy=yellow-585&stone1=emerald-Swarovsky&stone2=diamond-Swarovsky_4"
            ]
        },
        "14K Yellow Gold & White Sapphire": {
            "Product Name": "GLAMIRA Earring Varandus",
            "Product ID": "149768",
            "Product Full Link": "https://www.glamira.com/glamira-earring-varandus.html?accent=olivegreen&alloy=yellow-585&stone1=diamond-sapphire&stone2=diamond-sapphire",
            "Category ID": "1039",
            "Price": "$723.00",
            "Carat": "0.26 crt  - AAA",
            "Detail": {
                "accent": "olivegreen",
                "alloy": "yellow-585",
                "stone1": "diamond-sapphire",
                "stone2": "diamond-sapphire"
            },
            "Descript": "14K Yellow Gold & White Sapphire",
            "Product Image Path": [
                "D:\\VScode\\DE\\crawl_data\\Beautifulsoup\\Glamira\\project_glamira\\photo\\image_149768_GLAMIRA-Earring-Varandus_accent=olivegreen&alloy=yellow-585&stone1=diamond-sapphire&stone2=diamond-sapphire_1",
                "D:\\VScode\\DE\\crawl_data\\Beautifulsoup\\Glamira\\project_glamira\\photo\\image_149768_GLAMIRA-Earring-Varandus_accent=olivegreen&alloy=yellow-585&stone1=diamond-sapphire&stone2=diamond-sapphire_2",
                "D:\\VScode\\DE\\crawl_data\\Beautifulsoup\\Glamira\\project_glamira\\photo\\image_149768_GLAMIRA-Earring-Varandus_accent=olivegreen&alloy=yellow-585&stone1=diamond-sapphire&stone2=diamond-sapphire_3",
                "D:\\VScode\\DE\\crawl_data\\Beautifulsoup\\Glamira\\project_glamira\\photo\\image_149768_GLAMIRA-Earring-Varandus_accent=olivegreen&alloy=yellow-585&stone1=diamond-sapphire&stone2=diamond-sapphire_4"
            ]
        }
    },
    "GLAMIRA Earring Babestu": {
        "14K Yellow Gold & Citrine & Moissanite": {
            "Product Name": "GLAMIRA Earring Babestu",
            "Product ID": "149847",
            "Product Full Link": "https://www.glamira.com/glamira-earring-babestu.html?accent=darkindianred&alloy=yellow-585&stone1=citrine&stone2=labdiamond",
            "Category ID": "1039",
            "Price": "$622.00",
            "Carat": "0.448 crt  - AAA",
            "Detail": {
                "accent": "darkindianred",
                "alloy": "yellow-585",
                "stone1": "citrine",
                "stone2": "labdiamond"
            },
            "Descript": "14K Yellow Gold & Citrine & Moissanite",
            "Product Image Path": [
                "D:\\VScode\\DE\\crawl_data\\Beautifulsoup\\Glamira\\project_glamira\\photo\\image_149847_GLAMIRA-Earring-Babestu_accent=darkindianred&alloy=yellow-585&stone1=citrine&stone2=labdiamond_1",
                "D:\\VScode\\DE\\crawl_data\\Beautifulsoup\\Glamira\\project_glamira\\photo\\image_149847_GLAMIRA-Earring-Babestu_accent=darkindianred&alloy=yellow-585&stone1=citrine&stone2=labdiamond_2",
                "D:\\VScode\\DE\\crawl_data\\Beautifulsoup\\Glamira\\project_glamira\\photo\\image_149847_GLAMIRA-Earring-Babestu_accent=darkindianred&alloy=yellow-585&stone1=citrine&stone2=labdiamond_3",
                "D:\\VScode\\DE\\crawl_data\\Beautifulsoup\\Glamira\\project_glamira\\photo\\image_149847_GLAMIRA-Earring-Babestu_accent=darkindianred&alloy=yellow-585&stone1=citrine&stone2=labdiamond_4"
            ]
        },
        "14K Yellow Gold & Garnet & Moissanite": {
            "Product Name": "GLAMIRA Earring Babestu",
            "Product ID": "149847",
            "Product Full Link": "https://www.glamira.com/glamira-earring-babestu.html?accent=darkindianred&alloy=yellow-585&stone1=garnet&stone2=labdiamond",
            "Category ID": "1039",
            "Price": "$618.00",
            "Carat": "0.448 crt  - AAA",
            "Detail": {
                "accent": "darkindianred",
                "alloy": "yellow-585",
                "stone1": "garnet",
                "stone2": "labdiamond"
            },
            "Descript": "14K Yellow Gold & Garnet & Moissanite",
            "Product Image Path": [
                "D:\\VScode\\DE\\crawl_data\\Beautifulsoup\\Glamira\\project_glamira\\photo\\image_149847_GLAMIRA-Earring-Babestu_accent=darkindianred&alloy=yellow-585&stone1=garnet&stone2=labdiamond_1",
                "D:\\VScode\\DE\\crawl_data\\Beautifulsoup\\Glamira\\project_glamira\\photo\\image_149847_GLAMIRA-Earring-Babestu_accent=darkindianred&alloy=yellow-585&stone1=garnet&stone2=labdiamond_2",
                "D:\\VScode\\DE\\crawl_data\\Beautifulsoup\\Glamira\\project_glamira\\photo\\image_149847_GLAMIRA-Earring-Babestu_accent=darkindianred&alloy=yellow-585&stone1=garnet&stone2=labdiamond_3",
                "D:\\VScode\\DE\\crawl_data\\Beautifulsoup\\Glamira\\project_glamira\\photo\\image_149847_GLAMIRA-Earring-Babestu_accent=darkindianred&alloy=yellow-585&stone1=garnet&stone2=labdiamond_4"
            ]
        }
    },
    "GLAMIRA Earring Digitus": {
        "14K Yellow Gold & Fire-Opal & Moissanite": {
            "Product Name": "GLAMIRA Earring Digitus",
            "Product ID": "150045",
            "Product Full Link": "https://www.glamira.com/glamira-earring-digitus.html?alloy=yellow-585&stone1=fire-opal&stone2=labdiamond&stone3=labdiamond",
            "Category ID": "1039",
            "Price": "$1,226.00",
            "Carat": "1.296 crt  - AAA",
            "Detail": {
                "alloy": "yellow-585",
                "stone1": "fire-opal",
                "stone2": "labdiamond",
                "stone3": "labdiamond"
            },
            "Descript": "14K Yellow Gold & Fire-Opal & Moissanite",
            "Product Image Path": [
                "D:\\VScode\\DE\\crawl_data\\Beautifulsoup\\Glamira\\project_glamira\\photo\\image_150045_GLAMIRA-Earring-Digitus_alloy=yellow-585&stone1=fire-opal&stone2=labdiamond&stone3=labdiamond_1",
                "D:\\VScode\\DE\\crawl_data\\Beautifulsoup\\Glamira\\project_glamira\\photo\\image_150045_GLAMIRA-Earring-Digitus_alloy=yellow-585&stone1=fire-opal&stone2=labdiamond&stone3=labdiamond_2",
                "D:\\VScode\\DE\\crawl_data\\Beautifulsoup\\Glamira\\project_glamira\\photo\\image_150045_GLAMIRA-Earring-Digitus_alloy=yellow-585&stone1=fire-opal&stone2=labdiamond&stone3=labdiamond_3",
                "D:\\VScode\\DE\\crawl_data\\Beautifulsoup\\Glamira\\project_glamira\\photo\\image_150045_GLAMIRA-Earring-Digitus_alloy=yellow-585&stone1=fire-opal&stone2=labdiamond&stone3=labdiamond_4"
            ]
        },
        "14K Yellow Gold & Green Amethyst & Moissanite": {
            "Product Name": "GLAMIRA Earring Digitus",
            "Product ID": "150045",
            "Product Full Link": "https://www.glamira.com/glamira-earring-digitus.html?alloy=yellow-585&stone1=green-amethyst&stone2=labdiamond&stone3=labdiamond",
            "Category ID": "1039",
            "Price": "$1,212.00",
            "Carat": "1.296 crt  - AAA",
            "Detail": {
                "alloy": "yellow-585",
                "stone1": "green-amethyst",
                "stone2": "labdiamond",
                "stone3": "labdiamond"
            },
            "Descript": "14K Yellow Gold & Green Amethyst & Moissanite",
            "Product Image Path": [
                "D:\\VScode\\DE\\crawl_data\\Beautifulsoup\\Glamira\\project_glamira\\photo\\image_150045_GLAMIRA-Earring-Digitus_alloy=yellow-585&stone1=green-amethyst&stone2=labdiamond&stone3=labdiamond_1",
                "D:\\VScode\\DE\\crawl_data\\Beautifulsoup\\Glamira\\project_glamira\\photo\\image_150045_GLAMIRA-Earring-Digitus_alloy=yellow-585&stone1=green-amethyst&stone2=labdiamond&stone3=labdiamond_2",
                "D:\\VScode\\DE\\crawl_data\\Beautifulsoup\\Glamira\\project_glamira\\photo\\image_150045_GLAMIRA-Earring-Digitus_alloy=yellow-585&stone1=green-amethyst&stone2=labdiamond&stone3=labdiamond_3",
                "D:\\VScode\\DE\\crawl_data\\Beautifulsoup\\Glamira\\project_glamira\\photo\\image_150045_GLAMIRA-Earring-Digitus_alloy=yellow-585&stone1=green-amethyst&stone2=labdiamond&stone3=labdiamond_4"
            ]
        }
    },
    "GLAMIRA Earring Falldown": {
        "14K Yellow Gold & Swarovski Crystal": {
            "Product Name": "GLAMIRA Earring Falldown",
            "Product ID": "149827",
            "Product Full Link": "https://www.glamira.com/glamira-earring-falldown.html?alloy=yellow-585&stone1=diamond-Swarovsky",
            "Category ID": "1039",
            "Price": "$472.00",
            "Carat": "0.176 crt  - AAAAA",
            "Detail": {
                "alloy": "yellow-585",
                "stone1": "diamond-Swarovsky"
            },
            "Descript": "14K Yellow Gold & Swarovski Crystal",
            "Product Image Path": [
                "D:\\VScode\\DE\\crawl_data\\Beautifulsoup\\Glamira\\project_glamira\\photo\\image_149827_GLAMIRA-Earring-Falldown_alloy=yellow-585&stone1=diamond-Swarovsky_1",
                "D:\\VScode\\DE\\crawl_data\\Beautifulsoup\\Glamira\\project_glamira\\photo\\image_149827_GLAMIRA-Earring-Falldown_alloy=yellow-585&stone1=diamond-Swarovsky_2",
                "D:\\VScode\\DE\\crawl_data\\Beautifulsoup\\Glamira\\project_glamira\\photo\\image_149827_GLAMIRA-Earring-Falldown_alloy=yellow-585&stone1=diamond-Swarovsky_3",
                "D:\\VScode\\DE\\crawl_data\\Beautifulsoup\\Glamira\\project_glamira\\photo\\image_149827_GLAMIRA-Earring-Falldown_alloy=yellow-585&stone1=diamond-Swarovsky_4"
            ]
        }
    },
    "GLAMIRA Earring Teutum": {
        "14K Yellow Gold & Diamond": {
            "Product Name": "GLAMIRA Earring Teutum",
            "Product ID": "149921",
            "Product Full Link": "https://www.glamira.com/glamira-earring-teutum.html?alloy=yellow-585&stone1=diamond-Brillant",
            "Category ID": "1039",
            "Price": "$856.00",
            "Carat": "0.128 crt  - VS",
            "Detail": {
                "alloy": "yellow-585",
                "stone1": "diamond-Brillant"
            },
            "Descript": "14K Yellow Gold & Diamond",
            "Product Image Path": [
                "D:\\VScode\\DE\\crawl_data\\Beautifulsoup\\Glamira\\project_glamira\\photo\\image_149921_GLAMIRA-Earring-Teutum_alloy=yellow-585&stone1=diamond-Brillant_1",
                "D:\\VScode\\DE\\crawl_data\\Beautifulsoup\\Glamira\\project_glamira\\photo\\image_149921_GLAMIRA-Earring-Teutum_alloy=yellow-585&stone1=diamond-Brillant_2",
                "D:\\VScode\\DE\\crawl_data\\Beautifulsoup\\Glamira\\project_glamira\\photo\\image_149921_GLAMIRA-Earring-Teutum_alloy=yellow-585&stone1=diamond-Brillant_3",
                "D:\\VScode\\DE\\crawl_data\\Beautifulsoup\\Glamira\\project_glamira\\photo\\image_149921_GLAMIRA-Earring-Teutum_alloy=yellow-585&stone1=diamond-Brillant_4"
            ]
        }
    },
    "GLAMIRA Earring Gaisma - A": {
        "14K Yellow Gold & Emerald": {
            "Product Name": "GLAMIRA Earring Gaisma - A",
            "Product ID": "159473",
            "Product Full Link": "https://www.glamira.com/glamira-earring-gaisma-a.html?alloy=yellow-585&stone1=emerald",
            "Category ID": "1039",
            "Price": "$700.00",
            "Carat": "0.32 crt  - AAA",
            "Detail": {
                "alloy": "yellow-585",
                "stone1": "emerald"
            },
            "Descript": "14K Yellow Gold & Emerald",
            "Product Image Path": [
                "D:\\VScode\\DE\\crawl_data\\Beautifulsoup\\Glamira\\project_glamira\\photo\\image_159473_GLAMIRA-Earring-Gaisma---A_alloy=yellow-585&stone1=emerald_1",
                "D:\\VScode\\DE\\crawl_data\\Beautifulsoup\\Glamira\\project_glamira\\photo\\image_159473_GLAMIRA-Earring-Gaisma---A_alloy=yellow-585&stone1=emerald_2",
                "D:\\VScode\\DE\\crawl_data\\Beautifulsoup\\Glamira\\project_glamira\\photo\\image_159473_GLAMIRA-Earring-Gaisma---A_alloy=yellow-585&stone1=emerald_3",
                "D:\\VScode\\DE\\crawl_data\\Beautifulsoup\\Glamira\\project_glamira\\photo\\image_159473_GLAMIRA-Earring-Gaisma---A_alloy=yellow-585&stone1=emerald_4"
            ]
        }
    },
    "GLAMIRA Earring Valoa": {
        "14K Yellow Gold & Brown Diamond": {
            "Product Name": "GLAMIRA Earring Valoa",
            "Product ID": "149770",
            "Product Full Link": "https://www.glamira.com/glamira-earring-valoa.html?alloy=yellow-585&stone1=browndiamond",
            "Category ID": "1039",
            "Price": "$390.00",
            "Carat": "0.03 crt  - VS1",
            "Detail": {
                "alloy": "yellow-585",
                "stone1": "browndiamond"
            },
            "Descript": "14K Yellow Gold & Brown Diamond",
            "Product Image Path": [
                "D:\\VScode\\DE\\crawl_data\\Beautifulsoup\\Glamira\\project_glamira\\photo\\image_149770_GLAMIRA-Earring-Valoa_alloy=yellow-585&stone1=browndiamond_1",
                "D:\\VScode\\DE\\crawl_data\\Beautifulsoup\\Glamira\\project_glamira\\photo\\image_149770_GLAMIRA-Earring-Valoa_alloy=yellow-585&stone1=browndiamond_2",
                "D:\\VScode\\DE\\crawl_data\\Beautifulsoup\\Glamira\\project_glamira\\photo\\image_149770_GLAMIRA-Earring-Valoa_alloy=yellow-585&stone1=browndiamond_3",
                "D:\\VScode\\DE\\crawl_data\\Beautifulsoup\\Glamira\\project_glamira\\photo\\image_149770_GLAMIRA-Earring-Valoa_alloy=yellow-585&stone1=browndiamond_4"
            ]
        },
        "14K Yellow Gold & Swarovski Green": {
            "Product Name": "GLAMIRA Earring Valoa",
            "Product ID": "149770",
            "Product Full Link": "https://www.glamira.com/glamira-earring-valoa.html?alloy=yellow-585&stone1=emerald-Swarovsky",
            "Category ID": "1039",
            "Price": "$351.00",
            "Carat": "0.03 crt  - AAAAA",
            "Detail": {
                "alloy": "yellow-585",
                "stone1": "emerald-Swarovsky"
            },
            "Descript": "14K Yellow Gold & Swarovski Green",
            "Product Image Path": [
                "D:\\VScode\\DE\\crawl_data\\Beautifulsoup\\Glamira\\project_glamira\\photo\\image_149770_GLAMIRA-Earring-Valoa_alloy=yellow-585&stone1=emerald-Swarovsky_1",
                "D:\\VScode\\DE\\crawl_data\\Beautifulsoup\\Glamira\\project_glamira\\photo\\image_149770_GLAMIRA-Earring-Valoa_alloy=yellow-585&stone1=emerald-Swarovsky_2",
                "D:\\VScode\\DE\\crawl_data\\Beautifulsoup\\Glamira\\project_glamira\\photo\\image_149770_GLAMIRA-Earring-Valoa_alloy=yellow-585&stone1=emerald-Swarovsky_3",
                "D:\\VScode\\DE\\crawl_data\\Beautifulsoup\\Glamira\\project_glamira\\photo\\image_149770_GLAMIRA-Earring-Valoa_alloy=yellow-585&stone1=emerald-Swarovsky_4"
            ]
        },
        "14K Yellow Gold & White Sapphire": {
            "Product Name": "GLAMIRA Earring Valoa",
            "Product ID": "149770",
            "Product Full Link": "https://www.glamira.com/glamira-earring-valoa.html?alloy=yellow-585&stone1=diamond-sapphire",
            "Category ID": "1039",
            "Price": "$359.00",
            "Carat": "0.03 crt  - AAA",
            "Detail": {
                "alloy": "yellow-585",
                "stone1": "diamond-sapphire"
            },
            "Descript": "14K Yellow Gold & White Sapphire",
            "Product Image Path": [
                "D:\\VScode\\DE\\crawl_data\\Beautifulsoup\\Glamira\\project_glamira\\photo\\image_149770_GLAMIRA-Earring-Valoa_alloy=yellow-585&stone1=diamond-sapphire_1",
                "D:\\VScode\\DE\\crawl_data\\Beautifulsoup\\Glamira\\project_glamira\\photo\\image_149770_GLAMIRA-Earring-Valoa_alloy=yellow-585&stone1=diamond-sapphire_2",
                "D:\\VScode\\DE\\crawl_data\\Beautifulsoup\\Glamira\\project_glamira\\photo\\image_149770_GLAMIRA-Earring-Valoa_alloy=yellow-585&stone1=diamond-sapphire_3",
                "D:\\VScode\\DE\\crawl_data\\Beautifulsoup\\Glamira\\project_glamira\\photo\\image_149770_GLAMIRA-Earring-Valoa_alloy=yellow-585&stone1=diamond-sapphire_4"
            ]
        }
    },
    "GLAMIRA Earring Waiwai": {
        "14K Yellow Gold & Citrine & Moissanite": {
            "Product Name": "GLAMIRA Earring Waiwai",
            "Product ID": "149885",
            "Product Full Link": "https://www.glamira.com/glamira-earring-waiwai.html?accent=fossilgray&alloy=yellow-585&stone1=citrine&stone2=labdiamond",
            "Category ID": "1039",
            "Price": "$612.00",
            "Carat": "0.448 crt  - AAA",
            "Detail": {
                "accent": "fossilgray",
                "alloy": "yellow-585",
                "stone1": "citrine",
                "stone2": "labdiamond"
            },
            "Descript": "14K Yellow Gold & Citrine & Moissanite",
            "Product Image Path": [
                "D:\\VScode\\DE\\crawl_data\\Beautifulsoup\\Glamira\\project_glamira\\photo\\image_149885_GLAMIRA-Earring-Waiwai_accent=fossilgray&alloy=yellow-585&stone1=citrine&stone2=labdiamond_1",
                "D:\\VScode\\DE\\crawl_data\\Beautifulsoup\\Glamira\\project_glamira\\photo\\image_149885_GLAMIRA-Earring-Waiwai_accent=fossilgray&alloy=yellow-585&stone1=citrine&stone2=labdiamond_2",
                "D:\\VScode\\DE\\crawl_data\\Beautifulsoup\\Glamira\\project_glamira\\photo\\image_149885_GLAMIRA-Earring-Waiwai_accent=fossilgray&alloy=yellow-585&stone1=citrine&stone2=labdiamond_3",
                "D:\\VScode\\DE\\crawl_data\\Beautifulsoup\\Glamira\\project_glamira\\photo\\image_149885_GLAMIRA-Earring-Waiwai_accent=fossilgray&alloy=yellow-585&stone1=citrine&stone2=labdiamond_4"
            ]
        },
        "14K Yellow Gold & Garnet & Moissanite": {
            "Product Name": "GLAMIRA Earring Waiwai",
            "Product ID": "149885",
            "Product Full Link": "https://www.glamira.com/glamira-earring-waiwai.html?accent=fossilgray&alloy=yellow-585&stone1=garnet&stone2=labdiamond",
            "Category ID": "1039",
            "Price": "$608.00",
            "Carat": "0.448 crt  - AAA",
            "Detail": {
                "accent": "fossilgray",
                "alloy": "yellow-585",
                "stone1": "garnet",
                "stone2": "labdiamond"
            },
            "Descript": "14K Yellow Gold & Garnet & Moissanite",
            "Product Image Path": [
                "D:\\VScode\\DE\\crawl_data\\Beautifulsoup\\Glamira\\project_glamira\\photo\\image_149885_GLAMIRA-Earring-Waiwai_accent=fossilgray&alloy=yellow-585&stone1=garnet&stone2=labdiamond_1",
                "D:\\VScode\\DE\\crawl_data\\Beautifulsoup\\Glamira\\project_glamira\\photo\\image_149885_GLAMIRA-Earring-Waiwai_accent=fossilgray&alloy=yellow-585&stone1=garnet&stone2=labdiamond_2",
                "D:\\VScode\\DE\\crawl_data\\Beautifulsoup\\Glamira\\project_glamira\\photo\\image_149885_GLAMIRA-Earring-Waiwai_accent=fossilgray&alloy=yellow-585&stone1=garnet&stone2=labdiamond_3",
                "D:\\VScode\\DE\\crawl_data\\Beautifulsoup\\Glamira\\project_glamira\\photo\\image_149885_GLAMIRA-Earring-Waiwai_accent=fossilgray&alloy=yellow-585&stone1=garnet&stone2=labdiamond_4"
            ]
        }
    },
    "GLAMIRA Earring Gisteol": {
        "14K Yellow Gold & Swarovski Crystal": {
            "Product Name": "GLAMIRA Earring Gisteol",
            "Product ID": "149972",
            "Product Full Link": "https://www.glamira.com/glamira-earring-gisteol.html?alloy=yellow-585&stone1=diamond-Swarovsky&stone2=diamond-Swarovsky",
            "Category ID": "1039",
            "Price": "$783.00",
            "Carat": "0.16 crt  - AAAAA",
            "Detail": {
                "alloy": "yellow-585",
                "stone1": "diamond-Swarovsky",
                "stone2": "diamond-Swarovsky"
            },
            "Descript": "14K Yellow Gold & Swarovski Crystal",
            "Product Image Path": [
                "D:\\VScode\\DE\\crawl_data\\Beautifulsoup\\Glamira\\project_glamira\\photo\\image_149972_GLAMIRA-Earring-Gisteol_alloy=yellow-585&stone1=diamond-Swarovsky&stone2=diamond-Swarovsky_1",
                "D:\\VScode\\DE\\crawl_data\\Beautifulsoup\\Glamira\\project_glamira\\photo\\image_149972_GLAMIRA-Earring-Gisteol_alloy=yellow-585&stone1=diamond-Swarovsky&stone2=diamond-Swarovsky_2",
                "D:\\VScode\\DE\\crawl_data\\Beautifulsoup\\Glamira\\project_glamira\\photo\\image_149972_GLAMIRA-Earring-Gisteol_alloy=yellow-585&stone1=diamond-Swarovsky&stone2=diamond-Swarovsky_3",
                "D:\\VScode\\DE\\crawl_data\\Beautifulsoup\\Glamira\\project_glamira\\photo\\image_149972_GLAMIRA-Earring-Gisteol_alloy=yellow-585&stone1=diamond-Swarovsky&stone2=diamond-Swarovsky_4"
            ]
        }
    },
    "GLAMIRA Earring Toukchet": {
        "14K Yellow Gold & Fire-Opal & Moissanite": {
            "Product Name": "GLAMIRA Earring Toukchet",
            "Product ID": "150059",
            "Product Full Link": "https://www.glamira.com/glamira-earring-toukchet.html?accent=olivegreen&alloy=yellow-585&stone1=fire-opal&stone2=labdiamond",
            "Category ID": "1039",
            "Price": "$1,391.00",
            "Carat": "0.912 crt  - AAA",
            "Detail": {
                "accent": "olivegreen",
                "alloy": "yellow-585",
                "stone1": "fire-opal",
                "stone2": "labdiamond"
            },
            "Descript": "14K Yellow Gold & Fire-Opal & Moissanite",
            "Product Image Path": [
                "D:\\VScode\\DE\\crawl_data\\Beautifulsoup\\Glamira\\project_glamira\\photo\\image_150059_GLAMIRA-Earring-Toukchet_accent=olivegreen&alloy=yellow-585&stone1=fire-opal&stone2=labdiamond_1",
                "D:\\VScode\\DE\\crawl_data\\Beautifulsoup\\Glamira\\project_glamira\\photo\\image_150059_GLAMIRA-Earring-Toukchet_accent=olivegreen&alloy=yellow-585&stone1=fire-opal&stone2=labdiamond_2",
                "D:\\VScode\\DE\\crawl_data\\Beautifulsoup\\Glamira\\project_glamira\\photo\\image_150059_GLAMIRA-Earring-Toukchet_accent=olivegreen&alloy=yellow-585&stone1=fire-opal&stone2=labdiamond_3",
                "D:\\VScode\\DE\\crawl_data\\Beautifulsoup\\Glamira\\project_glamira\\photo\\image_150059_GLAMIRA-Earring-Toukchet_accent=olivegreen&alloy=yellow-585&stone1=fire-opal&stone2=labdiamond_4"
            ]
        },
        "14K Yellow Gold & Green Amethyst & Moissanite": {
            "Product Name": "GLAMIRA Earring Toukchet",
            "Product ID": "150059",
            "Product Full Link": "https://www.glamira.com/glamira-earring-toukchet.html?accent=olivegreen&alloy=yellow-585&stone1=green-amethyst&stone2=labdiamond",
            "Category ID": "1039",
            "Price": "$1,217.00",
            "Carat": "0.912 crt  - AAA",
            "Detail": {
                "accent": "olivegreen",
                "alloy": "yellow-585",
                "stone1": "green-amethyst",
                "stone2": "labdiamond"
            },
            "Descript": "14K Yellow Gold & Green Amethyst & Moissanite",
            "Product Image Path": [
                "D:\\VScode\\DE\\crawl_data\\Beautifulsoup\\Glamira\\project_glamira\\photo\\image_150059_GLAMIRA-Earring-Toukchet_accent=olivegreen&alloy=yellow-585&stone1=green-amethyst&stone2=labdiamond_1",
                "D:\\VScode\\DE\\crawl_data\\Beautifulsoup\\Glamira\\project_glamira\\photo\\image_150059_GLAMIRA-Earring-Toukchet_accent=olivegreen&alloy=yellow-585&stone1=green-amethyst&stone2=labdiamond_2",
                "D:\\VScode\\DE\\crawl_data\\Beautifulsoup\\Glamira\\project_glamira\\photo\\image_150059_GLAMIRA-Earring-Toukchet_accent=olivegreen&alloy=yellow-585&stone1=green-amethyst&stone2=labdiamond_3",
                "D:\\VScode\\DE\\crawl_data\\Beautifulsoup\\Glamira\\project_glamira\\photo\\image_150059_GLAMIRA-Earring-Toukchet_accent=olivegreen&alloy=yellow-585&stone1=green-amethyst&stone2=labdiamond_4"
            ]
        }
    },
    "GLAMIRA Earring Caligo": {
        "14K Yellow Gold & Diamond": {
            "Product Name": "GLAMIRA Earring Caligo",
            "Product ID": "149999",
            "Product Full Link": "https://www.glamira.com/glamira-earring-caligo.html?alloy=yellow-585&stone1=diamond-Brillant",
            "Category ID": "1039",
            "Price": "$368.00",
            "Carat": "0.016 crt  - VS",
            "Detail": {
                "alloy": "yellow-585",
                "stone1": "diamond-Brillant"
            },
            "Descript": "14K Yellow Gold & Diamond",
            "Product Image Path": [
                "D:\\VScode\\DE\\crawl_data\\Beautifulsoup\\Glamira\\project_glamira\\photo\\image_149999_GLAMIRA-Earring-Caligo_alloy=yellow-585&stone1=diamond-Brillant_1",
                "D:\\VScode\\DE\\crawl_data\\Beautifulsoup\\Glamira\\project_glamira\\photo\\image_149999_GLAMIRA-Earring-Caligo_alloy=yellow-585&stone1=diamond-Brillant_2",
                "D:\\VScode\\DE\\crawl_data\\Beautifulsoup\\Glamira\\project_glamira\\photo\\image_149999_GLAMIRA-Earring-Caligo_alloy=yellow-585&stone1=diamond-Brillant_3",
                "D:\\VScode\\DE\\crawl_data\\Beautifulsoup\\Glamira\\project_glamira\\photo\\image_149999_GLAMIRA-Earring-Caligo_alloy=yellow-585&stone1=diamond-Brillant_4"
            ]
        }
    },
    "GLAMIRA Earring Clavis": {
        "14K Yellow Gold & Emerald & White Sapphire": {
            "Product Name": "GLAMIRA Earring Clavis",
            "Product ID": "149838",
            "Product Full Link": "https://www.glamira.com/glamira-earring-clavis.html?alloy=yellow-585&stone1=emerald&stone2=diamond-sapphire",
            "Category ID": "1039",
            "Price": "$600.00",
            "Carat": "0.124 crt  - AAA",
            "Detail": {
                "alloy": "yellow-585",
                "stone1": "emerald",
                "stone2": "diamond-sapphire"
            },
            "Descript": "14K Yellow Gold & Emerald & White Sapphire",
            "Product Image Path": [
                "D:\\VScode\\DE\\crawl_data\\Beautifulsoup\\Glamira\\project_glamira\\photo\\image_149838_GLAMIRA-Earring-Clavis_alloy=yellow-585&stone1=emerald&stone2=diamond-sapphire_1",
                "D:\\VScode\\DE\\crawl_data\\Beautifulsoup\\Glamira\\project_glamira\\photo\\image_149838_GLAMIRA-Earring-Clavis_alloy=yellow-585&stone1=emerald&stone2=diamond-sapphire_2",
                "D:\\VScode\\DE\\crawl_data\\Beautifulsoup\\Glamira\\project_glamira\\photo\\image_149838_GLAMIRA-Earring-Clavis_alloy=yellow-585&stone1=emerald&stone2=diamond-sapphire_3",
                "D:\\VScode\\DE\\crawl_data\\Beautifulsoup\\Glamira\\project_glamira\\photo\\image_149838_GLAMIRA-Earring-Clavis_alloy=yellow-585&stone1=emerald&stone2=diamond-sapphire_4"
            ]
        }
    },
    "GLAMIRA Earring Twyla": {
        "14K Yellow Gold & Brown Diamond & Diamond": {
            "Product Name": "GLAMIRA Earring Twyla",
            "Product ID": "149772",
            "Product Full Link": "https://www.glamira.com/glamira-earring-twyla.html?alloy=yellow-585&stone1=browndiamond&stone2=diamond-Brillant",
            "Category ID": "1039",
            "Price": "$1,158.00",
            "Carat": "0.288 crt  - VS1",
            "Detail": {
                "alloy": "yellow-585",
                "stone1": "browndiamond",
                "stone2": "diamond-Brillant"
            },
            "Descript": "14K Yellow Gold & Brown Diamond & Diamond",
            "Product Image Path": [
                "D:\\VScode\\DE\\crawl_data\\Beautifulsoup\\Glamira\\project_glamira\\photo\\image_149772_GLAMIRA-Earring-Twyla_alloy=yellow-585&stone1=browndiamond&stone2=diamond-Brillant_1",
                "D:\\VScode\\DE\\crawl_data\\Beautifulsoup\\Glamira\\project_glamira\\photo\\image_149772_GLAMIRA-Earring-Twyla_alloy=yellow-585&stone1=browndiamond&stone2=diamond-Brillant_2",
                "D:\\VScode\\DE\\crawl_data\\Beautifulsoup\\Glamira\\project_glamira\\photo\\image_149772_GLAMIRA-Earring-Twyla_alloy=yellow-585&stone1=browndiamond&stone2=diamond-Brillant_3",
                "D:\\VScode\\DE\\crawl_data\\Beautifulsoup\\Glamira\\project_glamira\\photo\\image_149772_GLAMIRA-Earring-Twyla_alloy=yellow-585&stone1=browndiamond&stone2=diamond-Brillant_4"
            ]
        },
        "14K Yellow Gold & Swarovski Green & Swarovski Crystal": {
            "Product Name": "GLAMIRA Earring Twyla",
            "Product ID": "149772",
            "Product Full Link": "https://www.glamira.com/glamira-earring-twyla.html?alloy=yellow-585&stone1=emerald-Swarovsky&stone2=diamond-Swarovsky",
            "Category ID": "1039",
            "Price": "$779.00",
            "Carat": "0.288 crt  - AAAAA",
            "Detail": {
                "alloy": "yellow-585",
                "stone1": "emerald-Swarovsky",
                "stone2": "diamond-Swarovsky"
            },
            "Descript": "14K Yellow Gold & Swarovski Green & Swarovski Crystal",
            "Product Image Path": [
                "D:\\VScode\\DE\\crawl_data\\Beautifulsoup\\Glamira\\project_glamira\\photo\\image_149772_GLAMIRA-Earring-Twyla_alloy=yellow-585&stone1=emerald-Swarovsky&stone2=diamond-Swarovsky_1",
                "D:\\VScode\\DE\\crawl_data\\Beautifulsoup\\Glamira\\project_glamira\\photo\\image_149772_GLAMIRA-Earring-Twyla_alloy=yellow-585&stone1=emerald-Swarovsky&stone2=diamond-Swarovsky_2",
                "D:\\VScode\\DE\\crawl_data\\Beautifulsoup\\Glamira\\project_glamira\\photo\\image_149772_GLAMIRA-Earring-Twyla_alloy=yellow-585&stone1=emerald-Swarovsky&stone2=diamond-Swarovsky_3",
                "D:\\VScode\\DE\\crawl_data\\Beautifulsoup\\Glamira\\project_glamira\\photo\\image_149772_GLAMIRA-Earring-Twyla_alloy=yellow-585&stone1=emerald-Swarovsky&stone2=diamond-Swarovsky_4"
            ]
        }
    },
    "GLAMIRA Earring Bahati Set": {
        "14K Yellow Gold & Swarovski Crystal": {
            "Product Name": "GLAMIRA Earring Bahati Set",
            "Product ID": "149910",
            "Product Full Link": "https://www.glamira.com/glamira-earring-bahati-set.html?accent=darkindianred&alloy=yellow-585&stone1=diamond-Swarovsky&stone2=diamond-Swarovsky&stone3=diamond-Swarovsky",
            "Category ID": "1039",
            "Price": "$623.00",
            "Carat": "0.524 crt  - AAAAA",
            "Detail": {
                "accent": "darkindianred",
                "alloy": "yellow-585",
                "stone1": "diamond-Swarovsky",
                "stone2": "diamond-Swarovsky",
                "stone3": "diamond-Swarovsky"
            },
            "Descript": "14K Yellow Gold & Swarovski Crystal",
            "Product Image Path": [
                "D:\\VScode\\DE\\crawl_data\\Beautifulsoup\\Glamira\\project_glamira\\photo\\image_149910_GLAMIRA-Earring-Bahati-Set_accent=darkindianred&alloy=yellow-585&stone1=diamond-Swarovsky&stone2=diamond-Swarovsky&stone3=diamond-Swarovsky_1",
                "D:\\VScode\\DE\\crawl_data\\Beautifulsoup\\Glamira\\project_glamira\\photo\\image_149910_GLAMIRA-Earring-Bahati-Set_accent=darkindianred&alloy=yellow-585&stone1=diamond-Swarovsky&stone2=diamond-Swarovsky&stone3=diamond-Swarovsky_2",
                "D:\\VScode\\DE\\crawl_data\\Beautifulsoup\\Glamira\\project_glamira\\photo\\image_149910_GLAMIRA-Earring-Bahati-Set_accent=darkindianred&alloy=yellow-585&stone1=diamond-Swarovsky&stone2=diamond-Swarovsky&stone3=diamond-Swarovsky_3",
                "D:\\VScode\\DE\\crawl_data\\Beautifulsoup\\Glamira\\project_glamira\\photo\\image_149910_GLAMIRA-Earring-Bahati-Set_accent=darkindianred&alloy=yellow-585&stone1=diamond-Swarovsky&stone2=diamond-Swarovsky&stone3=diamond-Swarovsky_4"
            ]
        }
    },
    "GLAMIRA Earring Tajemnica": {
        "14K Yellow Gold & Fire-Opal & Moissanite": {
            "Product Name": "GLAMIRA Earring Tajemnica",
            "Product ID": "150115",
            "Product Full Link": "https://www.glamira.com/glamira-earring-tajemnica.html?accent=darkindianred&alloy=yellow-585&stone1=fire-opal&stone2=labdiamond&stone3=labdiamond",
            "Category ID": "1039",
            "Price": "$771.00",
            "Carat": "0.398 crt  - AAA",
            "Detail": {
                "accent": "darkindianred",
                "alloy": "yellow-585",
                "stone1": "fire-opal",
                "stone2": "labdiamond",
                "stone3": "labdiamond"
            },
            "Descript": "14K Yellow Gold & Fire-Opal & Moissanite",
            "Product Image Path": [
                "D:\\VScode\\DE\\crawl_data\\Beautifulsoup\\Glamira\\project_glamira\\photo\\image_150115_GLAMIRA-Earring-Tajemnica_accent=darkindianred&alloy=yellow-585&stone1=fire-opal&stone2=labdiamond&stone3=labdiamond_1",
                "D:\\VScode\\DE\\crawl_data\\Beautifulsoup\\Glamira\\project_glamira\\photo\\image_150115_GLAMIRA-Earring-Tajemnica_accent=darkindianred&alloy=yellow-585&stone1=fire-opal&stone2=labdiamond&stone3=labdiamond_2",
                "D:\\VScode\\DE\\crawl_data\\Beautifulsoup\\Glamira\\project_glamira\\photo\\image_150115_GLAMIRA-Earring-Tajemnica_accent=darkindianred&alloy=yellow-585&stone1=fire-opal&stone2=labdiamond&stone3=labdiamond_3",
                "D:\\VScode\\DE\\crawl_data\\Beautifulsoup\\Glamira\\project_glamira\\photo\\image_150115_GLAMIRA-Earring-Tajemnica_accent=darkindianred&alloy=yellow-585&stone1=fire-opal&stone2=labdiamond&stone3=labdiamond_4"
            ]
        }
    }
}